multiavatar/__init__.py
multiavatar/multiavatar.py
multiavatar-1.0.3.dist-info/LICENSE
multiavatar-1.0.3.dist-info/METADATA
multiavatar-1.0.3.dist-info/WHEEL
multiavatar-1.0.3.dist-info/top_level.txt
multiavatar-1.0.3.dist-info/RECORD
