Metadata-Version: 2.1
Name: multiavatar
Version: 1.0.3
Summary: Multicultural Avatar Generator in Python
Home-page: https://multiavatar.com
Author: Gie Katon
Author-email: git@giekaton.com
License: UNKNOWN
Project-URL: GitHub, https://github.com/multiavatar/multiavatar-python
Project-URL: Bug Tracker, https://github.com/multiavatar/multiavatar-python/issues
Project-URL: LICENSE, https://multiavatar.com/license
Platform: UNKNOWN
Classifier: Programming Language :: Python :: 3
Classifier: Operating System :: OS Independent
Requires-Python: >=3.6
